krkn_lib/__init__.py
krkn_lib/aws_tests/__init__.py
krkn_lib/aws_tests/test_krkn_telemetry_kubernetes.py
krkn_lib/aws_tests/test_krkn_telemetry_openshift.py
krkn_lib/elastic/__init__.py
krkn_lib/elastic/krkn_elastic.py
krkn_lib/k8s/__init__.py
krkn_lib/k8s/krkn_kubernetes.py
krkn_lib/k8s/pod_monitor/__init__.py
krkn_lib/k8s/pod_monitor/pod_monitor.py
krkn_lib/k8s/templates/hog_pod.j2
krkn_lib/k8s/templates/node_exec_pod.j2
krkn_lib/k8s/templates/service_hijacking_config_map.j2
krkn_lib/k8s/templates/service_hijacking_pod.j2
krkn_lib/k8s/templates/syn_flood_pod.j2
krkn_lib/models/__init__.py
krkn_lib/models/elastic/__init__.py
krkn_lib/models/elastic/models.py
krkn_lib/models/k8s/__init__.py
krkn_lib/models/k8s/models.py
krkn_lib/models/krkn/__init__.py
krkn_lib/models/krkn/models.py
krkn_lib/models/pod_monitor/__init__.py
krkn_lib/models/pod_monitor/models.py
krkn_lib/models/telemetry/__init__.py
krkn_lib/models/telemetry/models.py
krkn_lib/ocp/__init__.py
krkn_lib/ocp/krkn_openshift.py
krkn_lib/prometheus/__init__.py
krkn_lib/prometheus/krkn_prometheus.py
krkn_lib/telemetry/__init__.py
krkn_lib/telemetry/k8s/__init__.py
krkn_lib/telemetry/k8s/krkn_telemetry_kubernetes.py
krkn_lib/telemetry/ocp/__init__.py
krkn_lib/telemetry/ocp/krkn_telemetry_openshift.py
krkn_lib/tests/__init__.py
krkn_lib/tests/base_test.py
krkn_lib/tests/test_krkn_elastic.py
krkn_lib/tests/test_krkn_elastic_models.py
krkn_lib/tests/test_krkn_kubernetes_check.py
krkn_lib/tests/test_krkn_kubernetes_create.py
krkn_lib/tests/test_krkn_kubernetes_delete.py
krkn_lib/tests/test_krkn_kubernetes_exec.py
krkn_lib/tests/test_krkn_kubernetes_get.py
krkn_lib/tests/test_krkn_kubernetes_list.py
krkn_lib/tests/test_krkn_kubernetes_misc.py
krkn_lib/tests/test_krkn_kubernetes_models.py
krkn_lib/tests/test_krkn_kubernetes_pods_monitor.py
krkn_lib/tests/test_krkn_kubernetes_pods_monitor_models.py
krkn_lib/tests/test_krkn_openshift.py
krkn_lib/tests/test_krkn_prometheus.py
krkn_lib-5.1.12.dist-info/METADATA
krkn_lib-5.1.12.dist-info/WHEEL
krkn_lib-5.1.12.dist-info/licenses/LICENSE
krkn_lib-5.1.12.dist-info/RECORD
