Metadata-Version: 2.4
Name: krkn-lib
Version: 5.1.12
Summary: Foundation library for Kraken
License: Apache-2.0
License-File: LICENSE
Author: Red Hat Chaos Team
Requires-Python: >=3.9,<4.0
Classifier: License :: OSI Approved :: Apache Software License
Classifier: Programming Language :: Python :: 3
Classifier: Programming Language :: Python :: 3.9
Classifier: Programming Language :: Python :: 3.10
Classifier: Programming Language :: Python :: 3.11
Classifier: Programming Language :: Python :: 3.12
Classifier: Programming Language :: Python :: 3.13
Classifier: Programming Language :: Python :: 3.14
Requires-Dist: PyYAML (==6.0.1)
Requires-Dist: base64io (>=1.0.3,<2.0.0)
Requires-Dist: coverage (>=7.6.12,<8.0.0)
Requires-Dist: cython (==3.0)
Requires-Dist: deprecation (==2.1.0)
Requires-Dist: elasticsearch (==7.13.4)
Requires-Dist: elasticsearch-dsl (==7.4.1)
Requires-Dist: kubeconfig (>=1.1.1,<2.0.0)
Requires-Dist: kubernetes (==34.1.0)
Requires-Dist: numpy (==1.26.4)
Requires-Dist: prometheus-api-client (>=0.5.4,<0.6.0)
Requires-Dist: pytz (>=2023.3,<2024.0)
Requires-Dist: requests (>=2.29.0,<3.0.0)
Requires-Dist: sphinx-rtd-theme (>=1.2.2,<2.0.0)
Requires-Dist: sphinxnotes-markdown-builder (>=0.5.6,<0.6.0)
Requires-Dist: tzlocal (==5.1)
Requires-Dist: wheel (>=0.42.0,<0.43.0)
Project-URL: Homepage, https://github.com/redhat-chaos/krkn
